{
    "nike": {
      "id": 1,
      "title": "NIKE",
      "routeName": "nike",
      "items": [
        {
          "id": 2,
          "name": " Air Force 1",
          "image": "nike-0.png",
          "price": 150
        },
        {
          "id": 3,
          "name": "Air Zoom Pegasus 37",
          "image": "nike-1.png",
          "price": 150
        },
        {
          "id": 4,
          "name": "P 6000",
          "image": "nike-2.jpg",
          "price": 180
        },
        {
          "id": 5,
          "name": "Presto Fly",
          "image": "nike-3.png",
          "price": 120
        },
        {
          "id": 6,
          "name": "Air Max 87",
          "image": "nike-4.jpg",
          "price": 110
        },
        {
          "id": 7,
          "name": "Dunk Low",
          "image": "nike-5.png",
          "price": 110
        },
        {
          "id": 8,
          "name": "V2K Run",
          "image": "nike-6.png",
          "price": 100
        },
        {
          "id": 9,
          "name": "KD17",
          "image": "nike-7.png",
          "price": 150
        },
        {
          "id": 10,
          "name": "Air Force 1 Mid EasyOn",
          "image": "nike-8.png",
          "price": 115
        },
        {
          "id": 11,
          "name": "Blazer Low",
          "image": "nike-9.png",
          "price": 90
        },
        {
          "id": 12,
          "name": "Zoom Vomero 5 Premium",
          "image": "nike-10.png",
          "price": 150
        },
        {
          "id": 13,
          "name": "Calm",
          "image": "nike-11.png",
          "price": 60
        },
        {
          "id": 14,
          "name": "TC 7900",
          "image": "nike-12.png",
          "price": 160
        },
        {
          "id": 15,
          "name": "Air Max Plus Drift",
          "image": "nike-13.png",
          "price": 185
        },
        {
          "id": 16,
          "name": "Air Max 270",
          "image": "nike-14.png",
          "price": 150
        },
        {
          "id": 17,
          "name": "Court Borough Low Recraft",
          "image": "nike-15.png",
          "price": 47
        },
        {
          "id": 18,
          "name": "Air More Uptempo",
          "image": "nike-16.png",
          "price": 37
        },
        {
          "id": 19,
          "name": "Revolution 7 SE",
          "image": "nike-17.png",
          "price": 55
        },
        {
          "id": 20,
          "name": "Force 1 Low LV8 EasyOn",
          "image": "nike-18.png",
          "price": 56
        },
        {
          "id": 21,
          "name": "Force 1 Mid SE EasyOn",
          "image": "nike-19.png",
          "price": 54
        }
      ]
    }
  }